{
  "status": "ok",
  "filters": {
		"tags": [],
		"author": {
			"name" : "Kyla Medica",
			"id": "kyla-medica"
		}
  },
	"page": {
  	"current" : "1",
  	"total" : "1",
  	"items-total": "2",
  	"items-per-page" : "10"
  },
  "items": [
  	{
  		"tag" : "photo-essay",
  		"slug" : "why-shoot-film-8945",
  		"title" : "Why Shoot Film?",
  		"subtitle" : "Subtitle 2",
  		"id" : "0000001",
  		"post-date" : "1484179200",
  		"stats" : {
  			"images" : "3",
  			"words" : "300"
  		},
  		"author" : {
  			"name" : "Kayla Medica",
  			"id" : "kyla-medica"
  		},
  		"poster" : {
				"small" : "/images/pictures/poster.jpg",
				"medium" : "/images/pictures/poster.jpg",
				"large" : "/images/pictures/poster.jpg"
  		},
  		"summary" : "I bought my first film camera five years ago as a 17th birthday present to myself. I saved up my money and walked to a little old and dusty Kodak shop and bought myself a Nikkormat FT2 with a 50mm lens."
  	},
  	{
  		"tag" : "photo-essay",
  		"slug" : "why-shoot-film-8945",
  		"title" : "Why Shoot Film 2",
  		"subtitle" : "",
  		"id" : "0000003",
  		"post-date" : "1484179200",
  		"stats" : {
  			"images" : "1",
  			"words" : "300"
  		},
  		"author" : {
  			"name" : "Kayla Medica",
  			"id" : "kyla-medica"
  		},
  		"poster" : {
				"small" : "/images/pictures/poster.jpg",
				"medium" : "/images/pictures/poster.jpg",
				"large" : "/images/pictures/poster.jpg"
  		},
  		"summary" : "I bought my first film camera five years ago as a 17th birthday present to myself. I saved up my money and walked to a little old and dusty Kodak shop and bought myself a Nikkormat FT2 with a 50mm lens."
  	}
  ]
}
